nexusencrypter/__init__.py
nexusencrypter-0.0.6.dist-info/LICENSE
nexusencrypter-0.0.6.dist-info/METADATA
nexusencrypter-0.0.6.dist-info/WHEEL
nexusencrypter-0.0.6.dist-info/top_level.txt
nexusencrypter-0.0.6.dist-info/RECORD
