Metadata-Version: 2.1
Name: nexusencrypter
Version: 0.0.6
Summary: Nexus Encrypter Is A Fast Encrypting Library Where You Can Use: Random Keys, Custom Keys, Keys From .key Files. To Encrypt Text.
Home-page: https://github.com/goldenboys2011/Nexus-Encrypter-Library
Author: Odysseas Chryssos (@goldenboys2011)
Author-email: info@goldencube.dev
Project-URL: Bug Tracker, https://github.com/goldenboys2011/Nexus-Encrypter-Library/issues
Classifier: Programming Language :: Python :: 3
Classifier: License :: OSI Approved :: BSD License
Classifier: Operating System :: OS Independent
Requires-Python: >=3.6
License-File: LICENSE
